devtracker/__init__.py
devtracker/devtracker.py
dev_work_tracker-2.0.dist-info/LICENSE
dev_work_tracker-2.0.dist-info/METADATA
dev_work_tracker-2.0.dist-info/WHEEL
dev_work_tracker-2.0.dist-info/top_level.txt
dev_work_tracker-2.0.dist-info/RECORD
