Metadata-Version: 2.1
Name: dev-work-tracker
Version: 2.0
Summary: This is to track developers bug rate
Home-page: https://github.com/jagadeesh-l/dev-work-tracker
Author: Jagadeesh Lakshminarasimhan
Author-email: jagadeeshlaks@gmail.com
License: MIT
Platform: UNKNOWN
Classifier: Development Status :: 2 - Pre-Alpha
Classifier: Intended Audience :: Developers
Classifier: License :: OSI Approved :: MIT License
Classifier: Natural Language :: English
Classifier: Programming Language :: Python :: 3
Classifier: Programming Language :: Python :: 3.3
Classifier: Programming Language :: Python :: 3.4
Classifier: Programming Language :: Python :: 3.5
Classifier: Programming Language :: Python :: 3.6
Classifier: Programming Language :: Python :: 3.7
Classifier: Programming Language :: Python :: 3.8
Requires-Dist: jira
Requires-Dist: spacy
